{
  "date": "2026-03-20",
  "day": 9,
  "generatedAt": "2026-03-20T14:01:25.338Z",
  "summary": {
    "gameDev": {
      "completedVersions": [
        "v0.1",
        "v0.2",
        "v0.3",
        "v0.4",
        "v0.5",
        "v0.6",
        "v0.7",
        "v0.17",
        "v0.18",
        "v0.19",
        "v0.20",
        "v0.21",
        "v0.22",
        "v0.23",
        "v0.24",
        "v0.25",
        "v0.26",
        "v0.27",
        "v0.28",
        "v0.29",
        "v0.30",
        "v0.31",
        "v0.32",
        "v0.33"
      ],
      "totalTests": 602,
      "totalFeatures": 24,
      "latestVersion": "v0.33"
    },
    "quant": {
      "completedStages": [
        "quant-stage1",
        "quant-stage1b",
        "quant-stage2",
        "quant-stage3",
        "quant-stage4"
      ],
      "totalTests": 55,
      "latestStage": "quant-stage4"
    }
  },
  "newLearnings": [],
  "mistakes": [],
  "skillSuggestions": []
}